{
  "bias": [
    {
      "instrument": "GBP_USD",
      "current_bias": "bullish",
      "bias_strength": 1.0,
      "bias_since": "2026-07-14T09:53:37.415962+00:00",
      "contributing_signals": [
        {
          "tick": "2026-07-13T22:51:54.255274+00:00",
          "source": "strategy:momentum",
          "direction": "long",
          "confidence": 0.054
        },
        {
          "tick": "2026-07-13T23:50:17.194306+00:00",
          "source": "strategy:momentum",
          "direction": "long",
          "confidence": 0.046
        },
        {
          "tick": "2026-07-14T01:56:14.888308+00:00",
          "source": "strategy:momentum",
          "direction": "long",
          "confidence": 0.053
        },
        {
          "tick": "2026-07-14T04:48:24.632681+00:00",
          "source": "strategy:momentum",
          "direction": "long",
          "confidence": 0.057
        },
        {
          "tick": "2026-07-14T07:09:18.488698+00:00",
          "source": "strategy:momentum",
          "direction": "long",
          "confidence": 0.053
        },
        {
          "tick": "2026-07-14T09:53:37.267985+00:00",
          "source": "strategy:momentum",
          "direction": "long",
          "confidence": 0.07
        }
      ],
      "updated_at": "2026-07-14T09:53:37.428796+00:00",
      "direction": "bullish",
      "strength": 1.0,
      "total_pnl": -1.31,
      "trade_count": 27
    },
    {
      "instrument": "EUR_USD",
      "current_bias": "bearish",
      "bias_strength": 1.0,
      "bias_since": "2026-07-13T10:19:37.852021+00:00",
      "contributing_signals": [
        {
          "tick": "2026-07-13T22:51:54.278233+00:00",
          "source": "strategy:carry",
          "direction": "short",
          "confidence": 0.111
        },
        {
          "tick": "2026-07-13T23:50:17.217079+00:00",
          "source": "strategy:carry",
          "direction": "short",
          "confidence": 0.111
        },
        {
          "tick": "2026-07-14T01:56:14.912929+00:00",
          "source": "strategy:carry",
          "direction": "short",
          "confidence": 0.111
        },
        {
          "tick": "2026-07-14T04:48:24.650717+00:00",
          "source": "strategy:carry",
          "direction": "short",
          "confidence": 0.126
        },
        {
          "tick": "2026-07-14T07:09:18.509099+00:00",
          "source": "strategy:carry",
          "direction": "short",
          "confidence": 0.126
        },
        {
          "tick": "2026-07-14T07:09:18.484704+00:00",
          "source": "strategy:momentum",
          "direction": "short",
          "confidence": 0.021
        },
        {
          "tick": "2026-07-14T09:53:37.291540+00:00",
          "source": "strategy:carry",
          "direction": "short",
          "confidence": 0.122
        }
      ],
      "updated_at": "2026-07-14T09:53:37.426449+00:00",
      "direction": "bearish",
      "strength": 1.0,
      "total_pnl": -0.54,
      "trade_count": 14
    },
    {
      "instrument": "USD_JPY",
      "current_bias": "bullish",
      "bias_strength": 1.0,
      "bias_since": "2026-07-02T22:08:40.460916+00:00",
      "contributing_signals": [
        {
          "tick": "2026-07-13T22:51:54.284022+00:00",
          "source": "strategy:carry",
          "direction": "long",
          "confidence": 0.97
        },
        {
          "tick": "2026-07-13T22:51:54.259451+00:00",
          "source": "strategy:momentum",
          "direction": "long",
          "confidence": 0.021
        },
        {
          "tick": "2026-07-13T23:50:17.223083+00:00",
          "source": "strategy:carry",
          "direction": "long",
          "confidence": 0.97
        },
        {
          "tick": "2026-07-14T01:56:14.919227+00:00",
          "source": "strategy:carry",
          "direction": "long",
          "confidence": 0.976
        },
        {
          "tick": "2026-07-14T04:48:24.655313+00:00",
          "source": "strategy:carry",
          "direction": "long",
          "confidence": 0.98
        },
        {
          "tick": "2026-07-14T07:09:18.514713+00:00",
          "source": "strategy:carry",
          "direction": "long",
          "confidence": 0.981
        },
        {
          "tick": "2026-07-14T09:53:37.346881+00:00",
          "source": "strategy:mean_reversion",
          "direction": "long",
          "confidence": 0.847
        },
        {
          "tick": "2026-07-14T09:53:37.297233+00:00",
          "source": "strategy:carry",
          "direction": "long",
          "confidence": 0.98
        }
      ],
      "updated_at": "2026-07-14T09:53:37.421539+00:00",
      "direction": "bullish",
      "strength": 1.0,
      "total_pnl": 0.15,
      "trade_count": 46
    },
    {
      "instrument": "USD_CHF",
      "current_bias": "bullish",
      "bias_strength": 1.0,
      "bias_since": "2026-07-03T00:00:52.626444+00:00",
      "contributing_signals": [
        {
          "tick": "2026-07-13T22:51:54.287540+00:00",
          "source": "strategy:carry",
          "direction": "long",
          "confidence": 0.656
        },
        {
          "tick": "2026-07-13T22:51:54.262776+00:00",
          "source": "strategy:momentum",
          "direction": "long",
          "confidence": 0.13
        },
        {
          "tick": "2026-07-13T23:50:17.226917+00:00",
          "source": "strategy:carry",
          "direction": "long",
          "confidence": 0.656
        },
        {
          "tick": "2026-07-13T23:50:17.200959+00:00",
          "source": "strategy:momentum",
          "direction": "long",
          "confidence": 0.133
        },
        {
          "tick": "2026-07-14T01:56:14.922933+00:00",
          "source": "strategy:carry",
          "direction": "long",
          "confidence": 0.657
        },
        {
          "tick": "2026-07-14T01:56:14.895637+00:00",
          "source": "strategy:momentum",
          "direction": "long",
          "confidence": 0.126
        },
        {
          "tick": "2026-07-14T04:48:24.658034+00:00",
          "source": "strategy:carry",
          "direction": "long",
          "confidence": 0.663
        },
        {
          "tick": "2026-07-14T04:48:24.637895+00:00",
          "source": "strategy:momentum",
          "direction": "long",
          "confidence": 0.122
        },
        {
          "tick": "2026-07-14T07:09:18.517849+00:00",
          "source": "strategy:carry",
          "direction": "long",
          "confidence": 0.664
        },
        {
          "tick": "2026-07-14T07:09:18.493974+00:00",
          "source": "strategy:momentum",
          "direction": "long",
          "confidence": 0.123
        },
        {
          "tick": "2026-07-14T09:53:37.300912+00:00",
          "source": "strategy:carry",
          "direction": "long",
          "confidence": 0.653
        },
        {
          "tick": "2026-07-14T09:53:37.275170+00:00",
          "source": "strategy:momentum",
          "direction": "long",
          "confidence": 0.07
        }
      ],
      "updated_at": "2026-07-14T09:53:37.424412+00:00",
      "direction": "bullish",
      "strength": 1.0,
      "total_pnl": -4.04,
      "trade_count": 121
    },
    {
      "instrument": "EUR_GBP",
      "current_bias": "bearish",
      "bias_strength": 1.0,
      "bias_since": "2026-06-29T16:35:59.694416+00:00",
      "contributing_signals": [
        {
          "tick": "2026-07-13T22:51:54.296807+00:00",
          "source": "strategy:carry",
          "direction": "short",
          "confidence": 0.125
        },
        {
          "tick": "2026-07-13T22:51:54.271552+00:00",
          "source": "strategy:momentum",
          "direction": "short",
          "confidence": 0.06
        },
        {
          "tick": "2026-07-13T23:50:17.237207+00:00",
          "source": "strategy:carry",
          "direction": "short",
          "confidence": 0.126
        },
        {
          "tick": "2026-07-13T23:50:17.210141+00:00",
          "source": "strategy:momentum",
          "direction": "short",
          "confidence": 0.052
        },
        {
          "tick": "2026-07-14T01:56:14.932941+00:00",
          "source": "strategy:carry",
          "direction": "short",
          "confidence": 0.126
        },
        {
          "tick": "2026-07-14T01:56:14.905801+00:00",
          "source": "strategy:momentum",
          "direction": "short",
          "confidence": 0.055
        },
        {
          "tick": "2026-07-14T04:48:24.665283+00:00",
          "source": "strategy:carry",
          "direction": "short",
          "confidence": 0.134
        },
        {
          "tick": "2026-07-14T04:48:24.645260+00:00",
          "source": "strategy:momentum",
          "direction": "short",
          "confidence": 0.064
        },
        {
          "tick": "2026-07-14T07:09:18.526682+00:00",
          "source": "strategy:carry",
          "direction": "short",
          "confidence": 0.137
        },
        {
          "tick": "2026-07-14T07:09:18.502827+00:00",
          "source": "strategy:momentum",
          "direction": "short",
          "confidence": 0.073
        },
        {
          "tick": "2026-07-14T09:53:37.309847+00:00",
          "source": "strategy:carry",
          "direction": "short",
          "confidence": 0.137
        },
        {
          "tick": "2026-07-14T09:53:37.284916+00:00",
          "source": "strategy:momentum",
          "direction": "short",
          "confidence": 0.077
        }
      ],
      "updated_at": "2026-07-14T09:53:37.422993+00:00",
      "direction": "bearish",
      "strength": 1.0,
      "total_pnl": -2.49,
      "trade_count": 76
    },
    {
      "instrument": "XAU_USD",
      "current_bias": "bearish",
      "bias_strength": 0.8798,
      "bias_since": "2026-07-13T20:09:34.027998+00:00",
      "contributing_signals": [
        {
          "tick": "2026-07-13T22:51:54.274753+00:00",
          "source": "strategy:momentum",
          "direction": "short",
          "confidence": 0.064
        },
        {
          "tick": "2026-07-13T23:50:17.213388+00:00",
          "source": "strategy:momentum",
          "direction": "short",
          "confidence": 0.101
        },
        {
          "tick": "2026-07-14T01:56:14.909025+00:00",
          "source": "strategy:momentum",
          "direction": "short",
          "confidence": 0.022
        },
        {
          "tick": "2026-07-14T04:48:24.647821+00:00",
          "source": "strategy:momentum",
          "direction": "long",
          "confidence": 0.079
        },
        {
          "tick": "2026-07-14T07:09:18.505770+00:00",
          "source": "strategy:momentum",
          "direction": "short",
          "confidence": 0.099
        },
        {
          "tick": "2026-07-14T09:53:37.287926+00:00",
          "source": "strategy:momentum",
          "direction": "short",
          "confidence": 0.26
        }
      ],
      "updated_at": "2026-07-14T09:53:37.427587+00:00",
      "direction": "bearish",
      "strength": 0.8798,
      "total_pnl": 0.0,
      "trade_count": 0
    },
    {
      "instrument": "USD_CAD",
      "current_bias": "bearish",
      "bias_strength": 0.755,
      "bias_since": "2026-07-13T21:52:04.554077+00:00",
      "contributing_signals": [
        {
          "tick": "2026-07-13T22:51:54.268351+00:00",
          "source": "strategy:momentum",
          "direction": "short",
          "confidence": 0.051
        },
        {
          "tick": "2026-07-13T23:50:17.206729+00:00",
          "source": "strategy:momentum",
          "direction": "short",
          "confidence": 0.06
        },
        {
          "tick": "2026-07-14T01:56:14.902478+00:00",
          "source": "strategy:momentum",
          "direction": "short",
          "confidence": 0.066
        },
        {
          "tick": "2026-07-14T04:48:24.642840+00:00",
          "source": "strategy:momentum",
          "direction": "short",
          "confidence": 0.073
        },
        {
          "tick": "2026-07-14T07:09:18.499902+00:00",
          "source": "strategy:momentum",
          "direction": "short",
          "confidence": 0.08
        },
        {
          "tick": "2026-07-14T09:53:37.360007+00:00",
          "source": "strategy:mean_reversion",
          "direction": "long",
          "confidence": 0.368
        },
        {
          "tick": "2026-07-14T09:53:37.329594+00:00",
          "source": "strategy:breakout",
          "direction": "short",
          "confidence": 0.766
        },
        {
          "tick": "2026-07-14T09:53:37.281623+00:00",
          "source": "strategy:momentum",
          "direction": "short",
          "confidence": 0.133
        }
      ],
      "updated_at": "2026-07-14T09:53:37.416477+00:00",
      "direction": "bearish",
      "strength": 0.755,
      "total_pnl": 1.02,
      "trade_count": 81
    },
    {
      "instrument": "AUD_USD",
      "current_bias": "bearish",
      "bias_strength": 0.8552,
      "bias_since": "2026-07-12T22:39:40.405767+00:00",
      "contributing_signals": [
        {
          "tick": "2026-07-13T22:51:54.290915+00:00",
          "source": "strategy:carry",
          "direction": "short",
          "confidence": 0.15
        },
        {
          "tick": "2026-07-13T23:50:17.231194+00:00",
          "source": "strategy:carry",
          "direction": "short",
          "confidence": 0.15
        },
        {
          "tick": "2026-07-14T01:56:14.926610+00:00",
          "source": "strategy:carry",
          "direction": "short",
          "confidence": 0.151
        },
        {
          "tick": "2026-07-14T01:56:14.898929+00:00",
          "source": "strategy:momentum",
          "direction": "long",
          "confidence": 0.028
        },
        {
          "tick": "2026-07-14T04:48:24.660707+00:00",
          "source": "strategy:carry",
          "direction": "short",
          "confidence": 0.153
        },
        {
          "tick": "2026-07-14T04:48:24.640322+00:00",
          "source": "strategy:momentum",
          "direction": "long",
          "confidence": 0.058
        },
        {
          "tick": "2026-07-14T07:09:18.521014+00:00",
          "source": "strategy:carry",
          "direction": "short",
          "confidence": 0.153
        },
        {
          "tick": "2026-07-14T07:09:18.496988+00:00",
          "source": "strategy:momentum",
          "direction": "long",
          "confidence": 0.062
        },
        {
          "tick": "2026-07-14T09:53:37.355392+00:00",
          "source": "strategy:mean_reversion",
          "direction": "short",
          "confidence": 0.614
        },
        {
          "tick": "2026-07-14T09:53:37.304199+00:00",
          "source": "strategy:carry",
          "direction": "short",
          "confidence": 0.144
        },
        {
          "tick": "2026-07-14T09:53:37.278418+00:00",
          "source": "strategy:momentum",
          "direction": "long",
          "confidence": 0.098
        }
      ],
      "updated_at": "2026-07-14T09:53:37.419574+00:00",
      "direction": "bearish",
      "strength": 0.8552,
      "total_pnl": 1.48,
      "trade_count": 119
    }
  ]
}