{
  "bias": [
    {
      "instrument": "USD_CHF",
      "current_bias": "bullish",
      "bias_strength": 1.0,
      "bias_since": "2026-07-03T00:00:52.626444+00:00",
      "contributing_signals": [
        {
          "tick": "2026-07-24T02:33:29.944689+00:00",
          "source": "strategy:carry",
          "direction": "long",
          "confidence": 0.667
        },
        {
          "tick": "2026-07-24T02:33:29.917867+00:00",
          "source": "strategy:momentum",
          "direction": "long",
          "confidence": 0.067
        },
        {
          "tick": "2026-07-24T05:50:59.211541+00:00",
          "source": "strategy:carry",
          "direction": "long",
          "confidence": 0.669
        },
        {
          "tick": "2026-07-24T05:50:59.186405+00:00",
          "source": "strategy:momentum",
          "direction": "long",
          "confidence": 0.058
        },
        {
          "tick": "2026-07-24T08:27:26.060072+00:00",
          "source": "strategy:carry",
          "direction": "long",
          "confidence": 0.671
        },
        {
          "tick": "2026-07-24T08:27:26.037761+00:00",
          "source": "strategy:momentum",
          "direction": "long",
          "confidence": 0.036
        },
        {
          "tick": "2026-07-24T11:05:58.840568+00:00",
          "source": "strategy:carry",
          "direction": "long",
          "confidence": 0.671
        },
        {
          "tick": "2026-07-24T11:05:58.813348+00:00",
          "source": "strategy:momentum",
          "direction": "long",
          "confidence": 0.055
        },
        {
          "tick": "2026-07-24T13:41:38.965573+00:00",
          "source": "strategy:carry",
          "direction": "long",
          "confidence": 0.678
        },
        {
          "tick": "2026-07-24T13:41:38.932730+00:00",
          "source": "strategy:momentum",
          "direction": "long",
          "confidence": 0.069
        }
      ],
      "updated_at": "2026-07-24T13:41:39.091204+00:00",
      "direction": "bullish",
      "strength": 1.0,
      "total_pnl": -3.63,
      "trade_count": 141
    },
    {
      "instrument": "EUR_USD",
      "current_bias": "bearish",
      "bias_strength": 1.0,
      "bias_since": "2026-07-17T05:43:03.795688+00:00",
      "contributing_signals": [
        {
          "tick": "2026-07-24T02:33:29.934828+00:00",
          "source": "strategy:carry",
          "direction": "short",
          "confidence": 0.128
        },
        {
          "tick": "2026-07-24T02:33:29.907629+00:00",
          "source": "strategy:momentum",
          "direction": "short",
          "confidence": 0.031
        },
        {
          "tick": "2026-07-24T05:50:59.202365+00:00",
          "source": "strategy:carry",
          "direction": "short",
          "confidence": 0.129
        },
        {
          "tick": "2026-07-24T05:50:59.175878+00:00",
          "source": "strategy:momentum",
          "direction": "short",
          "confidence": 0.031
        },
        {
          "tick": "2026-07-24T08:27:26.051671+00:00",
          "source": "strategy:carry",
          "direction": "short",
          "confidence": 0.132
        },
        {
          "tick": "2026-07-24T11:05:58.830726+00:00",
          "source": "strategy:carry",
          "direction": "short",
          "confidence": 0.134
        },
        {
          "tick": "2026-07-24T13:41:38.955709+00:00",
          "source": "strategy:carry",
          "direction": "short",
          "confidence": 0.133
        }
      ],
      "updated_at": "2026-07-24T13:41:39.095218+00:00",
      "direction": "bearish",
      "strength": 1.0,
      "total_pnl": -1.09,
      "trade_count": 18
    },
    {
      "instrument": "EUR_GBP",
      "current_bias": "bearish",
      "bias_strength": 0.8373,
      "bias_since": "2026-07-22T08:17:37.326395+00:00",
      "contributing_signals": [
        {
          "tick": "2026-07-24T02:33:29.954019+00:00",
          "source": "strategy:carry",
          "direction": "short",
          "confidence": 0.131
        },
        {
          "tick": "2026-07-24T02:33:29.926783+00:00",
          "source": "strategy:momentum",
          "direction": "long",
          "confidence": 0.04
        },
        {
          "tick": "2026-07-24T05:50:59.220708+00:00",
          "source": "strategy:carry",
          "direction": "short",
          "confidence": 0.133
        },
        {
          "tick": "2026-07-24T05:50:59.195700+00:00",
          "source": "strategy:momentum",
          "direction": "long",
          "confidence": 0.037
        },
        {
          "tick": "2026-07-24T08:27:26.073918+00:00",
          "source": "strategy:carry",
          "direction": "short",
          "confidence": 0.132
        },
        {
          "tick": "2026-07-24T08:27:26.046313+00:00",
          "source": "strategy:momentum",
          "direction": "long",
          "confidence": 0.027
        },
        {
          "tick": "2026-07-24T11:05:58.850954+00:00",
          "source": "strategy:carry",
          "direction": "short",
          "confidence": 0.126
        },
        {
          "tick": "2026-07-24T11:05:58.823581+00:00",
          "source": "strategy:momentum",
          "direction": "long",
          "confidence": 0.034
        },
        {
          "tick": "2026-07-24T13:41:38.975615+00:00",
          "source": "strategy:carry",
          "direction": "short",
          "confidence": 0.128
        }
      ],
      "updated_at": "2026-07-24T13:41:39.087457+00:00",
      "direction": "bearish",
      "strength": 0.8373,
      "total_pnl": -2.98,
      "trade_count": 89
    },
    {
      "instrument": "USD_CAD",
      "current_bias": "bullish",
      "bias_strength": 0.7829,
      "bias_since": "2026-07-24T13:41:39.084697+00:00",
      "contributing_signals": [
        {
          "tick": "2026-07-24T02:33:29.923798+00:00",
          "source": "strategy:momentum",
          "direction": "short",
          "confidence": 0.064
        },
        {
          "tick": "2026-07-24T05:50:59.192652+00:00",
          "source": "strategy:momentum",
          "direction": "short",
          "confidence": 0.058
        },
        {
          "tick": "2026-07-24T08:27:26.043399+00:00",
          "source": "strategy:momentum",
          "direction": "short",
          "confidence": 0.061
        },
        {
          "tick": "2026-07-24T11:05:58.820318+00:00",
          "source": "strategy:momentum",
          "direction": "short",
          "confidence": 0.048
        },
        {
          "tick": "2026-07-24T13:41:38.996198+00:00",
          "source": "strategy:breakout",
          "direction": "long",
          "confidence": 0.591
        }
      ],
      "updated_at": "2026-07-24T13:41:39.085192+00:00",
      "direction": "bullish",
      "strength": 0.7829,
      "total_pnl": 1.33,
      "trade_count": 87
    },
    {
      "instrument": "XAU_USD",
      "current_bias": "bearish",
      "bias_strength": 0.5963,
      "bias_since": "2026-07-23T15:51:54.291223+00:00",
      "contributing_signals": [
        {
          "tick": "2026-07-24T02:33:29.929799+00:00",
          "source": "strategy:momentum",
          "direction": "short",
          "confidence": 0.207
        },
        {
          "tick": "2026-07-24T05:50:59.301220+00:00",
          "source": "strategy:volatility_breakout",
          "direction": "short",
          "confidence": 0.329
        },
        {
          "tick": "2026-07-24T05:50:59.198851+00:00",
          "source": "strategy:momentum",
          "direction": "short",
          "confidence": 0.248
        },
        {
          "tick": "2026-07-24T11:05:58.826981+00:00",
          "source": "strategy:momentum",
          "direction": "long",
          "confidence": 0.193
        },
        {
          "tick": "2026-07-24T13:41:38.951922+00:00",
          "source": "strategy:momentum",
          "direction": "long",
          "confidence": 0.166
        }
      ],
      "updated_at": "2026-07-24T13:41:39.096803+00:00",
      "direction": "bearish",
      "strength": 0.5963,
      "total_pnl": 0.0,
      "trade_count": 0
    },
    {
      "instrument": "GBP_USD",
      "current_bias": "bearish",
      "bias_strength": 1.0,
      "bias_since": "2026-07-21T15:39:35.877569+00:00",
      "contributing_signals": [
        {
          "tick": "2026-07-24T02:33:29.911820+00:00",
          "source": "strategy:momentum",
          "direction": "short",
          "confidence": 0.071
        },
        {
          "tick": "2026-07-24T05:50:59.180128+00:00",
          "source": "strategy:momentum",
          "direction": "short",
          "confidence": 0.067
        },
        {
          "tick": "2026-07-24T08:27:26.030487+00:00",
          "source": "strategy:momentum",
          "direction": "short",
          "confidence": 0.036
        },
        {
          "tick": "2026-07-24T11:05:58.805711+00:00",
          "source": "strategy:momentum",
          "direction": "short",
          "confidence": 0.033
        },
        {
          "tick": "2026-07-24T13:41:38.925241+00:00",
          "source": "strategy:momentum",
          "direction": "short",
          "confidence": 0.037
        }
      ],
      "updated_at": "2026-07-24T13:41:39.098109+00:00",
      "direction": "bearish",
      "strength": 1.0,
      "total_pnl": -1.51,
      "trade_count": 28
    },
    {
      "instrument": "AUD_USD",
      "current_bias": "bearish",
      "bias_strength": 0.6162,
      "bias_since": "2026-07-21T02:05:06.667987+00:00",
      "contributing_signals": [
        {
          "tick": "2026-07-24T02:33:29.948202+00:00",
          "source": "strategy:carry",
          "direction": "short",
          "confidence": 0.143
        },
        {
          "tick": "2026-07-24T02:33:29.920814+00:00",
          "source": "strategy:momentum",
          "direction": "long",
          "confidence": 0.065
        },
        {
          "tick": "2026-07-24T05:50:59.214858+00:00",
          "source": "strategy:carry",
          "direction": "short",
          "confidence": 0.143
        },
        {
          "tick": "2026-07-24T05:50:59.189589+00:00",
          "source": "strategy:momentum",
          "direction": "long",
          "confidence": 0.073
        },
        {
          "tick": "2026-07-24T08:27:26.063180+00:00",
          "source": "strategy:carry",
          "direction": "short",
          "confidence": 0.148
        },
        {
          "tick": "2026-07-24T08:27:26.040603+00:00",
          "source": "strategy:momentum",
          "direction": "long",
          "confidence": 0.107
        },
        {
          "tick": "2026-07-24T11:05:58.844370+00:00",
          "source": "strategy:carry",
          "direction": "short",
          "confidence": 0.15
        },
        {
          "tick": "2026-07-24T11:05:58.817053+00:00",
          "source": "strategy:momentum",
          "direction": "long",
          "confidence": 0.119
        },
        {
          "tick": "2026-07-24T13:41:38.969372+00:00",
          "source": "strategy:carry",
          "direction": "short",
          "confidence": 0.144
        },
        {
          "tick": "2026-07-24T13:41:38.936253+00:00",
          "source": "strategy:momentum",
          "direction": "long",
          "confidence": 0.079
        }
      ],
      "updated_at": "2026-07-24T13:41:39.088915+00:00",
      "direction": "bearish",
      "strength": 0.6162,
      "total_pnl": 1.25,
      "trade_count": 132
    },
    {
      "instrument": "USD_JPY",
      "current_bias": "bullish",
      "bias_strength": 1.0,
      "bias_since": "2026-07-02T22:08:40.460916+00:00",
      "contributing_signals": [
        {
          "tick": "2026-07-24T02:33:29.941252+00:00",
          "source": "strategy:carry",
          "direction": "long",
          "confidence": 0.971
        },
        {
          "tick": "2026-07-24T02:33:29.914891+00:00",
          "source": "strategy:momentum",
          "direction": "long",
          "confidence": 0.132
        },
        {
          "tick": "2026-07-24T05:50:59.208230+00:00",
          "source": "strategy:carry",
          "direction": "long",
          "confidence": 0.974
        },
        {
          "tick": "2026-07-24T05:50:59.183315+00:00",
          "source": "strategy:momentum",
          "direction": "long",
          "confidence": 0.125
        },
        {
          "tick": "2026-07-24T08:27:26.057004+00:00",
          "source": "strategy:carry",
          "direction": "long",
          "confidence": 0.983
        },
        {
          "tick": "2026-07-24T08:27:26.034769+00:00",
          "source": "strategy:momentum",
          "direction": "long",
          "confidence": 0.12
        },
        {
          "tick": "2026-07-24T11:05:58.837078+00:00",
          "source": "strategy:carry",
          "direction": "long",
          "confidence": 0.986
        },
        {
          "tick": "2026-07-24T11:05:58.810023+00:00",
          "source": "strategy:momentum",
          "direction": "long",
          "confidence": 0.111
        },
        {
          "tick": "2026-07-24T13:41:38.962054+00:00",
          "source": "strategy:carry",
          "direction": "long",
          "confidence": 0.987
        },
        {
          "tick": "2026-07-24T13:41:38.929496+00:00",
          "source": "strategy:momentum",
          "direction": "long",
          "confidence": 0.114
        }
      ],
      "updated_at": "2026-07-24T13:41:39.093154+00:00",
      "direction": "bullish",
      "strength": 1.0,
      "total_pnl": -0.01,
      "trade_count": 52
    }
  ]
}