{
  "bias": [
    {
      "instrument": "EUR_GBP",
      "current_bias": "bearish",
      "bias_strength": 1.0,
      "bias_since": "2026-06-29T16:35:59.694416+00:00",
      "contributing_signals": [
        {
          "tick": "2026-07-15T22:55:01.974243+00:00",
          "source": "strategy:carry",
          "direction": "short",
          "confidence": 0.092
        },
        {
          "tick": "2026-07-15T22:55:01.941449+00:00",
          "source": "strategy:momentum",
          "direction": "short",
          "confidence": 0.199
        },
        {
          "tick": "2026-07-15T23:55:40.471260+00:00",
          "source": "strategy:carry",
          "direction": "short",
          "confidence": 0.092
        },
        {
          "tick": "2026-07-15T23:55:40.449105+00:00",
          "source": "strategy:momentum",
          "direction": "short",
          "confidence": 0.192
        },
        {
          "tick": "2026-07-16T02:03:22.123621+00:00",
          "source": "strategy:carry",
          "direction": "short",
          "confidence": 0.09
        },
        {
          "tick": "2026-07-16T02:03:22.096475+00:00",
          "source": "strategy:momentum",
          "direction": "short",
          "confidence": 0.178
        },
        {
          "tick": "2026-07-16T05:35:59.585093+00:00",
          "source": "strategy:carry",
          "direction": "short",
          "confidence": 0.094
        },
        {
          "tick": "2026-07-16T05:35:59.559319+00:00",
          "source": "strategy:momentum",
          "direction": "short",
          "confidence": 0.19
        },
        {
          "tick": "2026-07-16T08:04:26.571667+00:00",
          "source": "strategy:carry",
          "direction": "short",
          "confidence": 0.094
        },
        {
          "tick": "2026-07-16T08:04:26.545453+00:00",
          "source": "strategy:momentum",
          "direction": "short",
          "confidence": 0.172
        },
        {
          "tick": "2026-07-16T10:54:50.679475+00:00",
          "source": "strategy:carry",
          "direction": "short",
          "confidence": 0.101
        },
        {
          "tick": "2026-07-16T10:54:50.655370+00:00",
          "source": "strategy:momentum",
          "direction": "short",
          "confidence": 0.133
        }
      ],
      "updated_at": "2026-07-16T10:54:50.782404+00:00",
      "direction": "bearish",
      "strength": 1.0,
      "total_pnl": -2.33,
      "trade_count": 77
    },
    {
      "instrument": "AUD_USD",
      "current_bias": "bearish",
      "bias_strength": 0.5222,
      "bias_since": "2026-07-16T10:54:50.779724+00:00",
      "contributing_signals": [
        {
          "tick": "2026-07-15T22:55:01.964789+00:00",
          "source": "strategy:carry",
          "direction": "short",
          "confidence": 0.147
        },
        {
          "tick": "2026-07-15T22:55:01.932510+00:00",
          "source": "strategy:momentum",
          "direction": "long",
          "confidence": 0.15
        },
        {
          "tick": "2026-07-15T23:55:40.466212+00:00",
          "source": "strategy:carry",
          "direction": "short",
          "confidence": 0.148
        },
        {
          "tick": "2026-07-15T23:55:40.443601+00:00",
          "source": "strategy:momentum",
          "direction": "long",
          "confidence": 0.144
        },
        {
          "tick": "2026-07-16T02:03:22.117310+00:00",
          "source": "strategy:carry",
          "direction": "short",
          "confidence": 0.142
        },
        {
          "tick": "2026-07-16T02:03:22.089923+00:00",
          "source": "strategy:momentum",
          "direction": "long",
          "confidence": 0.102
        },
        {
          "tick": "2026-07-16T05:35:59.579055+00:00",
          "source": "strategy:carry",
          "direction": "short",
          "confidence": 0.141
        },
        {
          "tick": "2026-07-16T05:35:59.553039+00:00",
          "source": "strategy:momentum",
          "direction": "long",
          "confidence": 0.122
        },
        {
          "tick": "2026-07-16T08:04:26.565530+00:00",
          "source": "strategy:carry",
          "direction": "short",
          "confidence": 0.147
        },
        {
          "tick": "2026-07-16T08:04:26.538886+00:00",
          "source": "strategy:momentum",
          "direction": "long",
          "confidence": 0.137
        },
        {
          "tick": "2026-07-16T10:54:50.673829+00:00",
          "source": "strategy:carry",
          "direction": "short",
          "confidence": 0.146
        },
        {
          "tick": "2026-07-16T10:54:50.649266+00:00",
          "source": "strategy:momentum",
          "direction": "long",
          "confidence": 0.142
        }
      ],
      "updated_at": "2026-07-16T10:54:50.784111+00:00",
      "direction": "bearish",
      "strength": 0.5222,
      "total_pnl": 1.18,
      "trade_count": 121
    },
    {
      "instrument": "XAU_USD",
      "current_bias": "bearish",
      "bias_strength": 1.0,
      "bias_since": "2026-07-15T15:23:08.243305+00:00",
      "contributing_signals": [
        {
          "tick": "2026-07-15T22:55:01.947094+00:00",
          "source": "strategy:momentum",
          "direction": "short",
          "confidence": 0.353
        },
        {
          "tick": "2026-07-15T23:55:40.451878+00:00",
          "source": "strategy:momentum",
          "direction": "short",
          "confidence": 0.304
        },
        {
          "tick": "2026-07-16T02:03:22.099823+00:00",
          "source": "strategy:momentum",
          "direction": "short",
          "confidence": 0.366
        },
        {
          "tick": "2026-07-16T05:35:59.562482+00:00",
          "source": "strategy:momentum",
          "direction": "short",
          "confidence": 0.426
        },
        {
          "tick": "2026-07-16T08:04:26.548681+00:00",
          "source": "strategy:momentum",
          "direction": "short",
          "confidence": 0.427
        },
        {
          "tick": "2026-07-16T10:54:50.658274+00:00",
          "source": "strategy:momentum",
          "direction": "short",
          "confidence": 0.473
        }
      ],
      "updated_at": "2026-07-16T10:54:50.790159+00:00",
      "direction": "bearish",
      "strength": 1.0,
      "total_pnl": 0.0,
      "trade_count": 0
    },
    {
      "instrument": "GBP_USD",
      "current_bias": "bullish",
      "bias_strength": 0.8031,
      "bias_since": "2026-07-15T15:23:08.243305+00:00",
      "contributing_signals": [
        {
          "tick": "2026-07-15T22:55:01.923497+00:00",
          "source": "strategy:momentum",
          "direction": "long",
          "confidence": 0.25
        },
        {
          "tick": "2026-07-15T23:55:40.435120+00:00",
          "source": "strategy:momentum",
          "direction": "long",
          "confidence": 0.251
        },
        {
          "tick": "2026-07-16T02:03:22.080781+00:00",
          "source": "strategy:momentum",
          "direction": "long",
          "confidence": 0.227
        },
        {
          "tick": "2026-07-16T05:35:59.543039+00:00",
          "source": "strategy:momentum",
          "direction": "long",
          "confidence": 0.255
        },
        {
          "tick": "2026-07-16T08:04:26.528933+00:00",
          "source": "strategy:momentum",
          "direction": "long",
          "confidence": 0.242
        },
        {
          "tick": "2026-07-16T10:54:50.738464+00:00",
          "source": "strategy:volatility_breakout",
          "direction": "short",
          "confidence": 0.247
        },
        {
          "tick": "2026-07-16T10:54:50.640053+00:00",
          "source": "strategy:momentum",
          "direction": "long",
          "confidence": 0.191
        }
      ],
      "updated_at": "2026-07-16T10:54:50.780179+00:00",
      "direction": "bullish",
      "strength": 0.8031,
      "total_pnl": -1.51,
      "trade_count": 28
    },
    {
      "instrument": "USD_JPY",
      "current_bias": "bullish",
      "bias_strength": 1.0,
      "bias_since": "2026-07-02T22:08:40.460916+00:00",
      "contributing_signals": [
        {
          "tick": "2026-07-15T22:55:01.957934+00:00",
          "source": "strategy:carry",
          "direction": "long",
          "confidence": 0.977
        },
        {
          "tick": "2026-07-15T22:55:01.927051+00:00",
          "source": "strategy:momentum",
          "direction": "long",
          "confidence": 0.058
        },
        {
          "tick": "2026-07-15T23:55:40.460234+00:00",
          "source": "strategy:carry",
          "direction": "long",
          "confidence": 0.977
        },
        {
          "tick": "2026-07-15T23:55:40.438085+00:00",
          "source": "strategy:momentum",
          "direction": "long",
          "confidence": 0.05
        },
        {
          "tick": "2026-07-16T02:03:22.109938+00:00",
          "source": "strategy:carry",
          "direction": "long",
          "confidence": 0.977
        },
        {
          "tick": "2026-07-16T02:03:22.084104+00:00",
          "source": "strategy:momentum",
          "direction": "long",
          "confidence": 0.052
        },
        {
          "tick": "2026-07-16T05:35:59.572206+00:00",
          "source": "strategy:carry",
          "direction": "long",
          "confidence": 0.978
        },
        {
          "tick": "2026-07-16T05:35:59.547328+00:00",
          "source": "strategy:momentum",
          "direction": "long",
          "confidence": 0.043
        },
        {
          "tick": "2026-07-16T08:04:26.558425+00:00",
          "source": "strategy:carry",
          "direction": "long",
          "confidence": 0.978
        },
        {
          "tick": "2026-07-16T08:04:26.532418+00:00",
          "source": "strategy:momentum",
          "direction": "long",
          "confidence": 0.029
        },
        {
          "tick": "2026-07-16T10:54:50.667423+00:00",
          "source": "strategy:carry",
          "direction": "long",
          "confidence": 0.982
        },
        {
          "tick": "2026-07-16T10:54:50.643109+00:00",
          "source": "strategy:momentum",
          "direction": "long",
          "confidence": 0.024
        }
      ],
      "updated_at": "2026-07-16T10:54:50.787110+00:00",
      "direction": "bullish",
      "strength": 1.0,
      "total_pnl": -0.12,
      "trade_count": 48
    },
    {
      "instrument": "USD_CAD",
      "current_bias": "bearish",
      "bias_strength": 1.0,
      "bias_since": "2026-07-13T21:52:04.554077+00:00",
      "contributing_signals": [
        {
          "tick": "2026-07-15T22:55:01.935648+00:00",
          "source": "strategy:momentum",
          "direction": "short",
          "confidence": 0.143
        },
        {
          "tick": "2026-07-15T23:55:40.446303+00:00",
          "source": "strategy:momentum",
          "direction": "short",
          "confidence": 0.143
        },
        {
          "tick": "2026-07-16T02:03:22.093191+00:00",
          "source": "strategy:momentum",
          "direction": "short",
          "confidence": 0.128
        },
        {
          "tick": "2026-07-16T05:35:59.556213+00:00",
          "source": "strategy:momentum",
          "direction": "short",
          "confidence": 0.136
        },
        {
          "tick": "2026-07-16T08:04:26.542189+00:00",
          "source": "strategy:momentum",
          "direction": "short",
          "confidence": 0.151
        },
        {
          "tick": "2026-07-16T10:54:50.652339+00:00",
          "source": "strategy:momentum",
          "direction": "short",
          "confidence": 0.156
        }
      ],
      "updated_at": "2026-07-16T10:54:50.791131+00:00",
      "direction": "bearish",
      "strength": 1.0,
      "total_pnl": 1.04,
      "trade_count": 83
    },
    {
      "instrument": "EUR_USD",
      "current_bias": "bearish",
      "bias_strength": 0.6847,
      "bias_since": "2026-07-16T10:54:50.779724+00:00",
      "contributing_signals": [
        {
          "tick": "2026-07-15T22:55:01.951971+00:00",
          "source": "strategy:carry",
          "direction": "short",
          "confidence": 0.123
        },
        {
          "tick": "2026-07-15T22:55:01.915646+00:00",
          "source": "strategy:momentum",
          "direction": "long",
          "confidence": 0.049
        },
        {
          "tick": "2026-07-15T23:55:40.454963+00:00",
          "source": "strategy:carry",
          "direction": "short",
          "confidence": 0.124
        },
        {
          "tick": "2026-07-15T23:55:40.431082+00:00",
          "source": "strategy:momentum",
          "direction": "long",
          "confidence": 0.056
        },
        {
          "tick": "2026-07-16T02:03:22.103658+00:00",
          "source": "strategy:carry",
          "direction": "short",
          "confidence": 0.122
        },
        {
          "tick": "2026-07-16T02:03:22.075988+00:00",
          "source": "strategy:momentum",
          "direction": "long",
          "confidence": 0.047
        },
        {
          "tick": "2026-07-16T05:35:59.566040+00:00",
          "source": "strategy:carry",
          "direction": "short",
          "confidence": 0.126
        },
        {
          "tick": "2026-07-16T05:35:59.538723+00:00",
          "source": "strategy:momentum",
          "direction": "long",
          "confidence": 0.061
        },
        {
          "tick": "2026-07-16T08:04:26.552337+00:00",
          "source": "strategy:carry",
          "direction": "short",
          "confidence": 0.127
        },
        {
          "tick": "2026-07-16T08:04:26.524433+00:00",
          "source": "strategy:momentum",
          "direction": "long",
          "confidence": 0.069
        },
        {
          "tick": "2026-07-16T10:54:50.661751+00:00",
          "source": "strategy:carry",
          "direction": "short",
          "confidence": 0.129
        },
        {
          "tick": "2026-07-16T10:54:50.635869+00:00",
          "source": "strategy:momentum",
          "direction": "long",
          "confidence": 0.058
        }
      ],
      "updated_at": "2026-07-16T10:54:50.788576+00:00",
      "direction": "bearish",
      "strength": 0.6847,
      "total_pnl": -0.88,
      "trade_count": 16
    },
    {
      "instrument": "USD_CHF",
      "current_bias": "bullish",
      "bias_strength": 0.9888,
      "bias_since": "2026-07-03T00:00:52.626444+00:00",
      "contributing_signals": [
        {
          "tick": "2026-07-15T22:55:01.961311+00:00",
          "source": "strategy:carry",
          "direction": "long",
          "confidence": 0.654
        },
        {
          "tick": "2026-07-15T23:55:40.463251+00:00",
          "source": "strategy:carry",
          "direction": "long",
          "confidence": 0.655
        },
        {
          "tick": "2026-07-15T23:55:40.440894+00:00",
          "source": "strategy:momentum",
          "direction": "short",
          "confidence": 0.026
        },
        {
          "tick": "2026-07-16T02:03:22.113621+00:00",
          "source": "strategy:carry",
          "direction": "long",
          "confidence": 0.653
        },
        {
          "tick": "2026-07-16T05:35:59.575609+00:00",
          "source": "strategy:carry",
          "direction": "long",
          "confidence": 0.656
        },
        {
          "tick": "2026-07-16T08:04:26.562017+00:00",
          "source": "strategy:carry",
          "direction": "long",
          "confidence": 0.662
        },
        {
          "tick": "2026-07-16T08:04:26.535718+00:00",
          "source": "strategy:momentum",
          "direction": "short",
          "confidence": 0.021
        },
        {
          "tick": "2026-07-16T10:54:50.670588+00:00",
          "source": "strategy:carry",
          "direction": "long",
          "confidence": 0.663
        },
        {
          "tick": "2026-07-16T10:54:50.646207+00:00",
          "source": "strategy:momentum",
          "direction": "long",
          "confidence": 0.025
        }
      ],
      "updated_at": "2026-07-16T10:54:50.785681+00:00",
      "direction": "bullish",
      "strength": 0.9888,
      "total_pnl": -4.37,
      "trade_count": 127
    }
  ]
}