{
  "trades": [
    {
      "id": 14,
      "stream": "strategy",
      "instrument": "XAU_USD",
      "direction": "short",
      "entry_price": 4608.52,
      "exit_price": null,
      "stop_loss": 4691.084285714286,
      "take_profit": 4484.673571428571,
      "position_size": 4.0,
      "pnl": null,
      "pnl_pips": null,
      "status": "open",
      "opened_at": "2026-03-19 15:25:39",
      "closed_at": null
    },
    {
      "id": 13,
      "stream": "strategy",
      "instrument": "USD_CHF",
      "direction": "long",
      "entry_price": 0.7907500000000001,
      "exit_price": null,
      "stop_loss": 0.7882176785714287,
      "take_profit": 0.7945484821428572,
      "position_size": 131630.0,
      "pnl": null,
      "pnl_pips": null,
      "status": "open",
      "opened_at": "2026-03-19 15:25:34",
      "closed_at": null
    },
    {
      "id": 12,
      "stream": "strategy",
      "instrument": "USD_JPY",
      "direction": "long",
      "entry_price": 158.394,
      "exit_price": null,
      "stop_loss": 157.9869642857143,
      "take_profit": 159.00455357142857,
      "position_size": 819.0,
      "pnl": null,
      "pnl_pips": null,
      "status": "open",
      "opened_at": "2026-03-19 15:25:33",
      "closed_at": null
    },
    {
      "id": 11,
      "stream": "strategy",
      "instrument": "XAU_USD",
      "direction": "short",
      "entry_price": 4612.92,
      "exit_price": null,
      "stop_loss": 4695.484285714286,
      "take_profit": 4489.073571428571,
      "position_size": 4.0,
      "pnl": null,
      "pnl_pips": null,
      "status": "open",
      "opened_at": "2026-03-19 15:25:31",
      "closed_at": null
    },
    {
      "id": 10,
      "stream": "news",
      "instrument": "EUR_USD",
      "direction": "short",
      "entry_price": 1.151605,
      "exit_price": null,
      "stop_loss": 1.154877142857143,
      "take_profit": 1.1466967857142856,
      "position_size": 101869.0,
      "pnl": null,
      "pnl_pips": null,
      "status": "open",
      "opened_at": "2026-03-19 15:23:36",
      "closed_at": null
    },
    {
      "id": 9,
      "stream": "news",
      "instrument": "BCO_USD",
      "direction": "short",
      "entry_price": 96.543,
      "exit_price": null,
      "stop_loss": 98.97857142857144,
      "take_profit": 92.88964285714286,
      "position_size": 137.0,
      "pnl": null,
      "pnl_pips": null,
      "status": "open",
      "opened_at": "2026-03-19 15:23:33",
      "closed_at": null
    },
    {
      "id": 8,
      "stream": "news",
      "instrument": "XAU_USD",
      "direction": "long",
      "entry_price": 4608.27,
      "exit_price": null,
      "stop_loss": 4525.705714285715,
      "take_profit": 4732.116428571429,
      "position_size": 4.0,
      "pnl": null,
      "pnl_pips": null,
      "status": "open",
      "opened_at": "2026-03-19 15:23:30",
      "closed_at": null
    },
    {
      "id": 7,
      "stream": "news",
      "instrument": "GBP_USD",
      "direction": "short",
      "entry_price": 1.33688,
      "exit_price": null,
      "stop_loss": 1.340845892857143,
      "take_profit": 1.3309311607142857,
      "position_size": 84049.0,
      "pnl": null,
      "pnl_pips": null,
      "status": "open",
      "opened_at": "2026-03-19 15:23:27",
      "closed_at": null
    }
  ]
}